mongo/__init__.py
mongo/connect.py
mongo/deps.py
mongo/document.py
mongo/document_meta.py
ext_mongo-0.4.0.dist-info/WHEEL
ext_mongo-0.4.0.dist-info/METADATA
ext_mongo-0.4.0.dist-info/RECORD
