Metadata-Version: 2.1
Name: ext-mongo
Version: 0.4.0
Summary: Extended mongoengine
License: MIT
Author-email: levch <levchenko.d.a1998@gmail.com>
Requires-Python: >=3.10
Requires-Dist: mongoengine>=0.27.0
Requires-Dist: parsenv>=0.2.2
